LICENSE
MANIFEST.in
README.rst
setup.py
pumuckl/__init__.py
pumuckl/module.py
pumuckl.egg-info/PKG-INFO
pumuckl.egg-info/SOURCES.txt
pumuckl.egg-info/dependency_links.txt
pumuckl.egg-info/entry_points.txt
pumuckl.egg-info/requires.txt
pumuckl.egg-info/top_level.txt