Metadata-Version: 1.1
Name: pumuckl
Version: 0.2.0
Summary: Check a Puppetfile for modules with newer versions
Home-page: https://github.com/Mayflower/pumuckl
Author: Robin Gloster
Author-email: robin.gloster@mayflower.de
License: GPL v3
Platform: UNKNOWN
Classifier: Programming Language :: Python
Classifier: Programming Language :: Python :: 3
Classifier: Programming Language :: Python :: 3.3
Classifier: Programming Language :: Python :: 3.4
Classifier: License :: OSI Approved :: GNU General Public License v3 (GPLv3)
Classifier: Operating System :: OS Independent
Classifier: Topic :: System :: Systems Administration
Classifier: Topic :: Utilities
Classifier: Intended Audience :: System Administrators
Classifier: Environment :: Console
